agents_manager/Agent.py
agents_manager/AgentManager.py
agents_manager/Container.py
agents_manager/Model.py
agents_manager/__init__.py
agents_manager/utils.py
agents_manager/models/Anthropic.py
agents_manager/models/DeepSeek.py
agents_manager/models/GenUi.py
agents_manager/models/Genai.py
agents_manager/models/Grok.py
agents_manager/models/Llama.py
agents_manager/models/OpenAi.py
agents_manager/models/__init__.py
agents_manager-1.4.6.dist-info/licenses/LICENCE
agents_manager-1.4.6.dist-info/METADATA
agents_manager-1.4.6.dist-info/WHEEL
agents_manager-1.4.6.dist-info/top_level.txt
agents_manager-1.4.6.dist-info/RECORD
